gain_with_hashi/__init__.py
gain_with_hashi/singleton.py
gain_with_hashi/utils.py
gain_with_hashi/api/__init__.py
gain_with_hashi/api/api.py
gain_with_hashi/api/api_login.py
gain_with_hashi/api/api_photo.py
gain_with_hashi/api/api_story.py
gain_with_hashi/api/api_video.py
gain_with_hashi/api/config.py
gain_with_hashi/api/devices.py
gain_with_hashi/api/prepare.py
gain_with_hashi/bot/__init__.py
gain_with_hashi/bot/bot.py
gain_with_hashi/bot/bot_archive.py
gain_with_hashi/bot/bot_block.py
gain_with_hashi/bot/bot_checkpoint.py
gain_with_hashi/bot/bot_comment.py
gain_with_hashi/bot/bot_delete.py
gain_with_hashi/bot/bot_direct.py
gain_with_hashi/bot/bot_filter.py
gain_with_hashi/bot/bot_follow.py
gain_with_hashi/bot/bot_get.py
gain_with_hashi/bot/bot_like.py
gain_with_hashi/bot/bot_photo.py
gain_with_hashi/bot/bot_stats.py
gain_with_hashi/bot/bot_story.py
gain_with_hashi/bot/bot_support.py
gain_with_hashi/bot/bot_unfollow.py
gain_with_hashi/bot/bot_unlike.py
gain_with_hashi/bot/bot_video.py
gain_with_hashi/bot/state/__init__.py
gain_with_hashi/bot/state/bot_cache.py
gain_with_hashi/bot/state/bot_state.py
gain_with_hashi-0.0.8.dist-info/LICENSE
gain_with_hashi-0.0.8.dist-info/METADATA
gain_with_hashi-0.0.8.dist-info/WHEEL
gain_with_hashi-0.0.8.dist-info/top_level.txt
gain_with_hashi-0.0.8.dist-info/RECORD
