Metadata-Version: 2.1
Name: gain-with-hashi
Version: 0.0.8
Summary: Gain Followers On Instagram
Home-page: http://instagram.com/hskoori
Author: kooriez
Author-email: <hashid0003@gmail.com.com>
License: Apache Software License 2.0
Keywords: instagram,bot,api,wrapper,hskoori
Platform: UNKNOWN
Classifier: Development Status :: 5 - Production/Stable
Classifier: Intended Audience :: Information Technology
Classifier: License :: OSI Approved :: Apache Software License
Classifier: Programming Language :: Python :: 2
Classifier: Programming Language :: Python :: 2.7
Classifier: Programming Language :: Python :: 3
Classifier: Programming Language :: Python :: 3.5
Classifier: Programming Language :: Python :: 3.6
Classifier: Programming Language :: Python :: 3.7
License-File: LICENSE
Requires-Dist: certifi (>=2019.11.28)
Requires-Dist: chardet (>=3.0.4)
Requires-Dist: future (>=0.18.2)
Requires-Dist: huepy (>=1.2.1)
Requires-Dist: idna (>=2.8)
Requires-Dist: pysocks (>=1.7.1)
Requires-Dist: pytz (>=2019.3)
Requires-Dist: requests (>=2.22.0)
Requires-Dist: requests-toolbelt (>=0.9.1)
Requires-Dist: responses (>=0.10.9)
Requires-Dist: schedule (>=0.6.0)
Requires-Dist: six (>=1.14.0)
Requires-Dist: tqdm (>=4.41.1)
Requires-Dist: urllib3 (>=1.25.7)
Requires-Dist: mock (>=3.0.5)
Requires-Dist: moviepy (>=1.0.1)
Requires-Dist: Pillow (>=6.2.2)
Requires-Dist: pytest (>=4.6.9)
Requires-Dist: pycryptodome (>=3.9.7)
